pyro_postgres-0.3.1.dist-info/METADATA
pyro_postgres-0.3.1.dist-info/WHEEL
pyro_postgres/__init__.py
pyro_postgres/__init__.pyi
pyro_postgres/async_.py
pyro_postgres/async_.pyi
pyro_postgres/error.py
pyro_postgres/error.pyi
pyro_postgres/py.typed
pyro_postgres/pyro_postgres.abi3.so
pyro_postgres/sync.py
pyro_postgres/sync.pyi
pyro_postgres-0.3.1.dist-info/RECORD
