Metadata-Version: 2.4
Name: pyro-postgres
Version: 0.3.1
Requires-Dist: typing-extensions
Requires-Python: >=3.10
